bitcalc/__init__.py
bitcalc/bits.py
bitcalc/interface.py
bitcalc/time.py
bitcalc-1.7.dist-info/LICENSE.md
bitcalc-1.7.dist-info/METADATA
bitcalc-1.7.dist-info/WHEEL
bitcalc-1.7.dist-info/entry_points.txt
bitcalc-1.7.dist-info/top_level.txt
bitcalc-1.7.dist-info/RECORD
