Metadata-Version: 2.1
Name: bitcalc
Version: 1.7
Summary: A python module for managing bit/byte unit manipulation
Home-page: https://github.com/miliarch/bitcalc
Author: Marcus Bowman
Author-email: miliarch.mb@gmail.com
License: MIT
Project-URL: Source Code, https://github.com/miliarch/bitcalc
Keywords: bit byte bitcalc binary decimal base-2 base-10 data rate transfer time
Requires-Python: >=3
License-File: LICENSE.md
